{
    "map": {
        "mapStyle": {
            "sat": "mapbox://styles/relnox/cjs9rb33k2pix1fo833uweyjd?fresh=true",
            "dark": "mapbox://styles/relnox/cjl58dpkq2jjp2rmzyrdvfsds?fresh=true",
            "blue": "mapbox://styles/relnox/ck0h5xn701bpr1dqs3he2lecq?fresh=true",
            "custom": "mapbox://styles/vlab-company/ckdy9814i47lg19p7eh0ms8gb"
        },
        "projectName": "hcm_test_v1",
        "gridTransparent": 180
    },
    "GEOGRIDDATA": {
        "color": [
            0,
            0,
            0,
            0
        ],
        "height": 0,
        "id": 0,
        "interactive": "Web",
        "name": "name"
    },
    "GEOGRID": {
        "features": [],
        "properties": {
            "geogrid_to_tui_mapping": {},
            "header": {
                "cellSize": 30,
                "latitude": 10.759316,
                "longitude": 106.705454,
                "tz": 7,
                "ncols": 20,
                "nrows": 20,
                "rotation": 0,
                "projection": "+proj=tmerc +lat_0=0 +lon_0=107.75 +k=0.9999 +x_0=500000 +y_0=0 +ellps=WGS84 +units=m +no_defs"
            },
            "types": {
                "Security land": {
                    "TypeCode": "CAN",
                    "IDSColor": 53,
                    "RGB": "255,80,70",
                    "color": "#ff5046"
                },
                "Land with public purposes": {
                    "TypeCode": "CCC",
                    "IDSColor": 59,
                    "RGB": "255,170,160",
                    "color": "#ffaaa0"
                },
                "Defense land": {
                    "TypeCode": "CQP",
                    "IDSColor": 52,
                    "RGB": "255,100,80",
                    "color": "#ff6450"
                },
                "Land for post and telecommunications": {
                    "TypeCode": "DBV",
                    "IDSColor": 67,
                    "RGB": "255,170,160",
                    "color": "#ffaaa0"
                },
                "Market land": {
                    "TypeCode": "DCH",
                    "IDSColor": 81,
                    "RGB": "255,170,160",
                    "color": "#ffaaa0"
                },
                "Land with historical-cultural relics": {
                    "TypeCode": "DDT",
                    "IDSColor": 84,
                    "RGB": "255,170,160",
                    "color": "#ffaaa0"
                },
                "Land for construction of education and training": {
                    "TypeCode": "DGD",
                    "IDSColor": 75,
                    "RGB": "255,170,160",
                    "color": "#ffaaa0"
                },
                "Transportation QHSDDTNMT": {
                    "TypeCode": "DGT",
                    "IDSColor": 60,
                    "RGB": "255,170,50",
                    "color": "#ffaa32"
                },
                "Land for energy facility": {
                    "TypeCode": "DNL",
                    "IDSColor": 66,
                    "RGB": "255,170,160",
                    "color": "#ffaaa0"
                },
                "Land for disposal, waste treatment": {
                    "TypeCode": "DRA",
                    "IDSColor": 85,
                    "RGB": "205,170,205",
                    "color": "#cdaacd"
                },
                "Irrigation land": {
                    "TypeCode": "DTL",
                    "IDSColor": 63,
                    "RGB": "170,255,255",
                    "color": "#aaffff"
                },
                "Land for construction of offices of non - business units": {
                    "TypeCode": "DTS",
                    "IDSColor": 48,
                    "RGB": "250,170,160",
                    "color": "#faaaa0"
                },
                "Land for construction of physical training and sport": {
                    "TypeCode": "DTT",
                    "IDSColor": 78,
                    "RGB": "255,170,160",
                    "color": "#ffaaa0"
                },
                "Land for construction of cultural": {
                    "TypeCode": "DVH",
                    "IDSColor": 69,
                    "RGB": "255,170,160",
                    "color": "#ffaaa0"
                },
                "Land for construction of health facilities": {
                    "TypeCode": "DYT",
                    "IDSColor": 72,
                    "RGB": "255,170,160",
                    "color": "#ffaaa0"
                },
                "Urban residential land": {
                    "TypeCode": "ODT",
                    "IDSColor": 42,
                    "RGB": "255,160,255",
                    "color": "#ffa0ff"
                },
                "Land non-agricultural production facilities": {
                    "TypeCode": "SKC",
                    "IDSColor": 56,
                    "RGB": "250,170,160",
                    "color": "#faaaa0"
                },
                "Land with rivers, streams, canals, springs": {
                    "TypeCode": "SON",
                    "IDSColor": 91,
                    "RGB": "160,255,255",
                    "color": "#a0ffff"
                },
                "Land for beliefs facility": {
                    "TypeCode": "TIN",
                    "IDSColor": 88,
                    "RGB": "255,170,160",
                    "color": "#ffaaa0"
                },
                "Land for religious facility": {
                    "TypeCode": "TON",
                    "IDSColor": 87,
                    "RGB": "255,170,160",
                    "color": "#ffaaa0"
                },
                "Land for construction of offices": {
                    "TypeCode": "TSC",
                    "IDSColor": 45,
                    "RGB": "255,170,160",
                    "color": "#ffaaa0"
                },
                "Thematic park (amusement park)": {
                    "TypeCode": "CXCD",
                    "IDSColor": 94,
                    "RGB": "0,127,0",
                    "color": "#007f00"
                },
                "Greenary - park land QHPK": {
                    "TypeCode": "CXCL",
                    "IDSColor": 126,
                    "RGB": "0,76,57",
                    "color": "#004c39"
                },
                "Water surface QHPK": {
                    "TypeCode": "MN",
                    "IDSColor": 152,
                    "RGB": "0,82,165",
                    "color": "#0052a5"
                },
                "Educational NCDT": {
                    "TypeCode": "NCDT",
                    "IDSColor": 144,
                    "RGB": "0,95,127",
                    "color": "#005f7f"
                },
                "Educational GD2": {
                    "TypeCode": "GD2",
                    "IDSColor": 24,
                    "RGB": "127,31,0",
                    "color": "#7f1f00"
                },
                "Office - production and trading": {
                    "TypeCode": "CQCT",
                    "IDSColor": 34,
                    "RGB": "127,63,0",
                    "color": "#7f3f00"
                },
                "Educational GD1": {
                    "TypeCode": "GD1",
                    "IDSColor": 15,
                    "RGB": "127,63,63",
                    "color": "#7f3f3f"
                },
                "School": {
                    "TypeCode": "GD",
                    "IDSColor": 15,
                    "RGB": "127,63,63",
                    "color": "#7f3f3f"
                },
                "Existing and Renovated Residential": {
                    "TypeCode": "NNO",
                    "IDSColor": 42,
                    "RGB": "165,124,0",
                    "color": "#a57c00"
                },
                "Wetland": {
                    "TypeCode": "DK",
                    "IDSColor": 254,
                    "RGB": "204,204,204",
                    "color": "#cccccc"
                },
                "Public Facility": {
                    "TypeCode": "CCDVO",
                    "IDSColor": 1,
                    "RGB": "255,0,0",
                    "color": "#ff0000"
                },
                "Resort/Outdoor entertainment": {
                    "TypeCode": "CCDT",
                    "IDSColor": 1,
                    "RGB": "255,0,0",
                    "color": "#ff0000"
                },
                "Mixed-use": {
                    "TypeCode": "HH",
                    "IDSColor": 21,
                    "RGB": "255,159,127",
                    "color": "#ff9f7f"
                },
                "Transportation QHPK": {
                    "TypeCode": "DGT",
                    "IDSColor": 7,
                    "RGB": "255,255,255",
                    "color": "#ffffff"
                },
                "National defense - security": {
                    "TypeCode": "ANQP",
                    "IDSColor": 69,
                    "RGB": "33,38,19",
                    "color": "#212613"
                },
                "Production land - warehouse": {
                    "TypeCode": "KTBB",
                    "IDSColor": 177,
                    "RGB": "38,38,126",
                    "color": "#26267e"
                },
                "Sport - Greenery": {
                    "TypeCode": "CXDVO",
                    "IDSColor": 76,
                    "RGB": "38,76,0",
                    "color": "#264c00"
                },
                "Religious": {
                    "TypeCode": "TGDT",
                    "IDSColor": 16,
                    "RGB": "76,0,0",
                    "color": "#4c0000"
                },
                "Greenary - park land QHSSK": {
                    "TypeCode": "CXDT",
                    "IDSColor": 72,
                    "RGB": "82,165,0",
                    "color": "#52a500"
                },
                "Technical Infrastructure": {
                    "TypeCode": "HTKT",
                    "IDSColor": 195,
                    "RGB": "95,63,127",
                    "color": "#5f3f7f"
                },
                "Transportation QHSSK": {
                    "TypeCode": "DGT",
                    "IDSColor": 7,
                    "RGB": "255,255,255",
                    "color": "#ffffff"
                },
                "Water surface": {
                    "TypeCode": "MN",
                    "IDSColor": 152,
                    "RGB": "0,82,165",
                    "color": "#0052a5"
                },
                "Open Space": {
                    "TypeCode": "CXCD",
                    "IDSColor": 94,
                    "RGB": "0,127,0",
                    "color": "#007f00"
                },
                "New Residential": {
                    "TypeCode": "DVO",
                    "IDSColor": 30,
                    "RGB": "255,127,0",
                    "color": "#ff7f00"
                },
                "Hotel": {
                    "TypeCode": "DL",
                    "IDSColor": 210,
                    "RGB": "255,0,255",
                    "color": "#ff00ff"
                },
                "Community": {
                    "TypeCode": "CCDT",
                    "IDSColor": 1,
                    "RGB": "255,0,0",
                    "color": "#ff0000"
                },
                "Schools": {
                    "TypeCode": "GD",
                    "IDSColor": 15,
                    "RGB": "127,63,63",
                    "color": "#7f3f3f"
                },
                "Religion - Relic": {
                    "TypeCode": "TGDT",
                    "IDSColor": 16,
                    "RGB": "76,0,0",
                    "color": "#4c0000"
                },
                "Existing agency": {
                    "TypeCode": "CQCT",
                    "IDSColor": 34,
                    "RGB": "127,63,0",
                    "color": "#7f3f00"
                },
                "Institutional Buildings": {
                    "TypeCode": "NCDT",
                    "IDSColor": 144,
                    "RGB": "0,95,127",
                    "color": "#005f7f"
                },
                "Urban Hybrid": {
                    "TypeCode": "HH",
                    "IDSColor": 21,
                    "RGB": "255,159,127",
                    "color": "#ff9f7f"
                },
                "Parking Garage": {
                    "TypeCode": "HTKT",
                    "IDSColor": 195,
                    "RGB": "95,63,127",
                    "color": "#5f3f7f"
                },
                "Cemetery": {
                    "TypeCode": "NT",
                    "IDSColor": 251,
                    "RGB": "101,101,101",
                    "color": "#656565"
                }
            }
        },
        "type": "FeatureCollection"
    }
}