{
    "ANQP": "rgb(33,38,19)",
    "CCDT": "rgb(255,0,0)",
    "CCDVO": "rgb(255,0,0)",
    "CN": "rgb(82,0,165)",
    "CQCT": "rgb(127,63,0)",
    "CXCD": "rgb(0,127,0)",
    "CXCL": "rgb(0,76,57)",
    "CXDT": "rgb(82,165,0)",
    "CXDVO": "rgb(38,76,0)",
    "DGT": "rgb(130,130,130)",
    "DL": "rgb(255,0,255)",
    "GD": "rgb(127,31,0)",
    "GD1": "rgb(127,63,63)",
    "GD2": "rgb(127,31,0)",
    "HH": "rgb(255,159,127)",
    "HTKT": "rgb(95,63,127)",
    "KTBB": "rgb(38,38,126)",
    "LN": "rgb(0,38,38)",
    "NCDT": "rgb(0,95,127)",
    "NN": "rgb(0,255,0)",
    "NNO": "rgb(165,124,0)",
    "NT": "rgb(101,101,101)",
    "OLX": "rgb(76,76,38)",
    "TDTT": "rgb(0,127,0)",
    "TGDT": "rgb(76,0,0)",
    "TTYT": "rgb(255,0,191)",
    "DK": "rgb(204,204,204)",
    "MN": "rgb(170,218,255)"
}